globalmart_api_ilt/__init__.py
globalmart_api_ilt/oops.py
globalmart_api_elt-0.1.dist-info/METADATA
globalmart_api_elt-0.1.dist-info/WHEEL
globalmart_api_elt-0.1.dist-info/top_level.txt
globalmart_api_elt-0.1.dist-info/RECORD
