Metadata-Version: 2.1
Name: globalmart-api-elt
Version: 0.1
Summary: The package contains the logic to fetch the data from API and convert 
Author: Enqurious
Author-email: enqurious@mentorskool.com
License: MIT
Requires-Dist: pandas
Requires-Dist: requests
